{
  "info": { "name": "Natal charts database", "version": "1.0.0", "charts": 1 },
  "charts": [
    {
      "name": "Matias Arno",
      "birthdate": "7-3-1997",
      "time": 2123,
      "asc": 214,
      "sun": 347,
      "moon": 332,
      "mercury": 344,
      "venus": 341,
      "mars": 180,
      "jupiter": 310,
      "saturn": 7,
      "uranus": 306,
      "neptune": 299,
      "pluto": 245
    },
    {
      "name": "Ludovica Squirrel",
      "birthdate": "7-3-1950",
      "time": 212,
      "asc": 212,
      "sun": 212,
      "moon": 212,
      "mercury": 212,
      "venus": 212,
      "mars": 212,
      "jupiter": 212,
      "saturn": 212,
      "uranus": 212,
      "neptune": 212,
      "pluto": 212
    }
  ]
}
